b10_kernel/__init__.py
b10_kernel/activation.py
b10_kernel/common_ops.cpython-312-x86_64-linux-gnu.so
b10_kernel/cute/__init__.py
b10_kernel/cute/copy_utils.py
b10_kernel/cute/reduce.py
b10_kernel/cute/reduction_base.py
b10_kernel/cute/rmsnorm.py
b10_kernel/cute/utils.py
b10_kernel/fp4_quant.py
b10_kernel/norm.py
b10_kernel/preload_env.py
b10_kernel/triton/__init__.py
b10_kernel/triton/quantization.py
b10_kernel/triton/rope.py
b10_kernel/utils.py
b10_kernel/version.py
b10_kernel-0.1.5.dist-info/METADATA
b10_kernel-0.1.5.dist-info/WHEEL
b10_kernel-0.1.5.dist-info/RECORD
