Metadata-Version: 2.1
Name: b10-kernel
Version: 0.1.5
Summary: Baseten Kernel Library
Keywords: machine learning,gpu,cuda,kernels,pytorch
Author-Email: Ke Bao <ke.bao@baseten.co>
Maintainer-Email: Ke Bao <ke.bao@baseten.co>, Pankaj Gupta <pankaj@baseten.co>, Yikai Zhu <yikai.zhu@baseten.co>, Shounak Ray <shounak.ray@baseten.co>
Classifier: Development Status :: 3 - Alpha
Classifier: Intended Audience :: Developers
Classifier: License :: OSI Approved :: MIT License
Classifier: Programming Language :: Python :: 3
Classifier: Programming Language :: Python :: 3.12
Classifier: Programming Language :: C++
Classifier: Topic :: Scientific/Engineering :: Artificial Intelligence
Classifier: Topic :: Software Development :: Libraries :: Python Modules
Requires-Python: >=3.12
Requires-Dist: nvidia-cutlass-dsl==4.2.0
Requires-Dist: torch==2.8.0
Provides-Extra: test
Requires-Dist: pytest>=8.0.0; extra == "test"
Provides-Extra: dev
Requires-Dist: pytest>=8.0.0; extra == "dev"
Requires-Dist: ruff; extra == "dev"
Requires-Dist: scikit-build-core>=0.10; extra == "dev"
